flopymetascript/__init__.py
flopymetascript/__main__.py
flopymetascript/flopymetascript.py
flopymetascript/flopymetascript_old.py
flopymetascript/metafunctions.py
flopymetascript/metafunctions_old.py
flopymetascript/metafunctions_old2.py
flopymetascript/model.py
flopymetascript/parameter.py
flopymetascript/test_model.py
flopymetascript/version.py
flopymetascript/yapf_play.py
flopymetascript-1.0.0.dist-info/DESCRIPTION.rst
flopymetascript-1.0.0.dist-info/METADATA
flopymetascript-1.0.0.dist-info/RECORD
flopymetascript-1.0.0.dist-info/WHEEL
flopymetascript-1.0.0.dist-info/entry_points.txt
flopymetascript-1.0.0.dist-info/metadata.json
flopymetascript-1.0.0.dist-info/top_level.txt
