Metadata-Version: 2.0
Name: flopymetascript
Version: 1.0.0
Summary: Converts a zip with MODFLOW input files to a zip containing Flopy script
Home-page: https://github.com/bdestombe/flopymetascript
Author: Bas des Tombe
Author-email: bdestombe@gmail.com
License: MIT
Download-URL: https://github.com/bdestombe/flopymetascript/archive/1.0.0.tar.gz
Keywords: flopy,groundwater,hydrology
Platform: Windows
Platform: Mac OS-X
Classifier: Development Status :: 4 - Beta
Classifier: Topic :: Scientific/Engineering
Classifier: Programming Language :: Python :: 3 :: Only
Classifier: License :: OSI Approved :: BSD License
Classifier: Natural Language :: English
Classifier: License :: OSI Approved :: MIT License
Requires-Dist: flopy (>=3.2)
Requires-Dist: nbconvert (>=5.1)
Requires-Dist: nbformat (>=4.3)
Requires-Dist: numpy (>=1.12)
Requires-Dist: yapf
